jaxacc/__init__.py
jaxacc/core.py
jaxacc/jit.py
jaxacc-0.1.1.dist-info/METADATA
jaxacc-0.1.1.dist-info/WHEEL
jaxacc-0.1.1.dist-info/top_level.txt
jaxacc-0.1.1.dist-info/RECORD
