Metadata-Version: 2.1
Name: jaxacc
Version: 0.1.1
Summary: Optimization tools for JAX
Home-page: https://github.com/yourusername/jaxacc
Author: Your Name
Author-email: your.email@example.com
Classifier: Programming Language :: Python :: 3
Classifier: Operating System :: OS Independent
Requires-Python: >=3.8
Requires-Dist: jax>=0.3.0
Requires-Dist: numpy>=1.20.0
